network_connector/__init__.py
network_connector/interface_connector.py
network_connector/ssh_connector.py
network_connector/version.py
network_connector-0.0.2.dist-info/METADATA
network_connector-0.0.2.dist-info/WHEEL
network_connector-0.0.2.dist-info/top_level.txt
network_connector-0.0.2.dist-info/RECORD
